<?xml version="1.0" encoding="utf-8" ?>
<!-- Generated on 6/18/2013 4:52:24 PM -->
<CodeGen>
  <Componenttype>BaseClass</Componenttype>

  <CreationInfo Target_ProgrammingLanguage="C#"
                Target_ProgrammingLanguage_Revision="2.0"
                Target_ProgrammingLanguage_LibraryName="CLE_L1_dlmc_cmn"
                Target_SQL="MySQL"
                Target_SQL_Revision="8" />

  <Base_Tables>
    <Base_Table Name="RES_QST_Facade_AvailableProperty"
                IsClass="true"
                IsClass_Namespace="CL1_RES_QST"
                IsClass_Corresponding_DBTable="res_qst_facade_availableproperties" >
      <Members>
		<ClassMember Name="RES_QST_Facade_AvailablePropertyID" Type="Guid" IsObjectPrimaryKey="true"/>
		<ClassMember Name="RES_QST_Questionnaire_Version_RefID" Type="Guid" />
		<ClassMember Name="RES_STR_Facade_Property_RefID" Type="Guid" />
		<ClassMember Name="Creation_Timestamp" Type="DateTime" IsDateOfCreationField="true"/>
		<ClassMember Name="IsDeleted" Type="Boolean" IsDeletedField="true"/>
		<ClassMember Name="Tenant_RefID" Type="Guid" IsTenantField="true"/>
	
      </Members>
    </Base_Table>
  </Base_Tables>
</CodeGen>


