<?xml version="1.0" encoding="utf-8" ?>
<!-- Generated on 7/8/2014 1:23:35 PM -->
<CodeGen>
  <Componenttype>BaseClass</Componenttype>

  <Meta>
    <Name></Name>
    <Namespace></Namespace>
    <Description></Description>
    <Tags></Tags>
  </Meta>

  <CreationInfo Target_ProgrammingLanguage="C#"
                Target_ProgrammingLanguage_Revision="2.0"
                Target_ProgrammingLanguage_LibraryName="CLE_L1_dlmc_cmn"
                Target_SQL="MySQL"
                Target_SQL_Revision="8" />

  <Base_Tables>
    <Base_Table Name="LOG_SHP_RSH_ReceivableCreditNote_2_ReceiptPosition"
                IsClass="true"
                IsClass_Namespace="CL1_LOG_SHP_RSH"
                IsClass_Corresponding_DBTable="log_shp_rsh_receivablecreditnote_2_receiptposition" >
      <Members>
		<ClassMember Name="AssignmentID" Type="Guid" IsObjectPrimaryKey="true"/>
		<ClassMember Name="LOG_SHP_ReturnShipment_ReceivableCreditNote_Position_RefID" Type="Guid" />
		<ClassMember Name="LOG_RCP_Receipt_Position_RefID" Type="Guid" />
		<ClassMember Name="CompensationValue" Type="double" />
		<ClassMember Name="IsFullCompensationForReceivableCreditNotePosition" Type="Boolean" />
		<ClassMember Name="Creation_Timestamp" Type="DateTime" IsDateOfCreationField="true"/>
		<ClassMember Name="Tenant_RefID" Type="Guid" IsTenantField="true"/>
		<ClassMember Name="IsDeleted" Type="Boolean" IsDeletedField="true"/>
	
      </Members>
    </Base_Table>
  </Base_Tables>
</CodeGen>


