<?xml version="1.0" encoding="utf-8" ?>
<!-- Generated on 7/4/2013 11:11:49 AM -->
<CodeGen>
  <Componenttype>BaseClass</Componenttype>

  <CreationInfo Target_ProgrammingLanguage="C#"
                Target_ProgrammingLanguage_Revision="2.0"
                Target_ProgrammingLanguage_LibraryName="CLE_L1_dlmc_cmn"
                Target_SQL="MySQL"
                Target_SQL_Revision="8" />

  <Base_Tables>
    <Base_Table Name="RES_DUD_RevisionGroup"
                IsClass="true"
                IsClass_Namespace="CL1_RES_DUD"
                IsClass_Corresponding_DBTable="res_dud_revisiongroup" >
      <Members>
		<ClassMember Name="RES_DUD_Revision_GroupID" Type="Guid" IsObjectPrimaryKey="true"/>
		<ClassMember Name="RealestateProperty_RefID" Type="Guid" />
		<ClassMember Name="RevisionGroup_Name" Type="String" />
		<ClassMember Name="RevisionGroup_SubmittedBy_Account_RefID" Type="Guid" />
		<ClassMember Name="RevisionGroup_Comment" Type="String" />
		<ClassMember Name="Creation_Timestamp" Type="DateTime" IsDateOfCreationField="true"/>
		<ClassMember Name="IsDeleted" Type="Boolean" IsDeletedField="true"/>
		<ClassMember Name="Tenant_RefID" Type="Guid" IsTenantField="true"/>
	
      </Members>
    </Base_Table>
  </Base_Tables>
</CodeGen>


