<?xml version="1.0" encoding="utf-8" ?>
<CodeGen createdOn="14/10/2013 11:24:40">
  <Componenttype>AtomicMethod</Componenttype>

  <Meta>
    <Name>Save_Case</Name>
    <Namespace>DataImporter.DBMethods.Case.Atomic.Manipulation</Namespace>
    <Description></Description>
    <Tags></Tags>
  </Meta>

  <PlattformInfo  Target_Method_ProgrammingLanguage="C#"
									Target_Method_ProgrammingLanguage_Revision="3.5"
									Target_SQL="MySQL"
									Target_SQL_Revision="8"
									Create_Webservice_Interface="true"
									Create_Webservice_Interface_ServerPlattform="C#"
									Create_Webservice_Interface_ServerPlattform_Revision="3.5"
									Create_Webservice_Interface_ApplicationPlattform="FLEX"
									Create_Webservice_Interface_ApplicationPlattform_Revision="4.5"
									/>

  <CreationInfo Method_Namespace="DataImporter.DBMethods.Case.Atomic.Manipulation"
								Method_ClassName="cls_Save_Case"
								Method_Name="Save_Case"
								ApplicationPlattform_WebServiceName=""
								ApplicationPlattform_Namespace=""
								/>

  <Parameters IsClass="true" Name="P_CAS_SC_1711">
    <Members>
      <ClassMember Name="patient_id" Type="Guid"  />
      <ClassMember Name="practice_id" Type="Guid"  />
      <ClassMember Name="treatment_date" Type="DateTime"  />
      <ClassMember Name="drug_id" Type="Guid"  />
      <ClassMember Name="diagnose_id" Type="Guid"  />
      <ClassMember Name="is_left_eye" Type="Boolean"  />
      <ClassMember Name="is_confirmed" Type="Boolean"  />
      <ClassMember Name="treatment_doctor_id" Type="Guid"  />
      <ClassMember Name="aftercare_doctor_practice_id" Type="Guid"  />
      <ClassMember Name="treatment_gpos" Type="String"  />
      <ClassMember Name="aftercare_gpos" Type="String"  />
      <ClassMember Name="bevacizumab_gpos" Type="String"  />
      <ClassMember Name="management_fee_gpos" Type="String"  />

    </Members>
  </Parameters>

  <ResultInfo Returns_just_the_status_of_the_operation="false"
				Returns_a_StandardDataType_or_StadardDataTypeArray="true"
				Returns_an_Object_or_ObjectArray="false">

    <StandardReturnType_Definition returnType="Guid" IsArray="false" />
  </ResultInfo>

</CodeGen>
